aspose/threed/py.typed
aspose/pycore/py.typed
aspose/pycore/__init__.pyi
aspose/pyreflection/py.typed
aspose/pyreflection/__init__.pyi
aspose/pydrawing/py.typed
aspose/pydrawing/__init__.pyi
aspose/pydrawing/design.pyi
aspose/pydrawing/drawing2d.pyi
aspose/pydrawing/imaging.pyi
aspose/pydrawing/printing.pyi
aspose/pydrawing/text.pyi
aspose/threed/__init__.pyi
aspose/threed/animation/__init__.pyi
aspose/threed/deformers/__init__.pyi
aspose/threed/entities/__init__.pyi
aspose/threed/formats/__init__.pyi
aspose/threed/formats/gltf/__init__.pyi
aspose/threed/profiles/__init__.pyi
aspose/threed/render/__init__.pyi
aspose/threed/shading/__init__.pyi
aspose/threed/utilities/__init__.pyi
.__pyi_patched
aspose/__init__.py
aspose/pycore.cp310-win_amd64.pyd
aspose/pycore.cp311-win_amd64.pyd
aspose/pycore.cp35-win_amd64.pyd
aspose/pycore.cp36-win_amd64.pyd
aspose/pycore.cp37-win_amd64.pyd
aspose/pycore.cp38-win_amd64.pyd
aspose/pycore.cp39-win_amd64.pyd
aspose/pygc.cp310-win_amd64.pyd
aspose/pygc.cp311-win_amd64.pyd
aspose/pygc.cp35-win_amd64.pyd
aspose/pygc.cp36-win_amd64.pyd
aspose/pygc.cp37-win_amd64.pyd
aspose/pygc.cp38-win_amd64.pyd
aspose/pygc.cp39-win_amd64.pyd
aspose/pyreflection.cp310-win_amd64.pyd
aspose/pyreflection.cp311-win_amd64.pyd
aspose/pyreflection.cp35-win_amd64.pyd
aspose/pyreflection.cp36-win_amd64.pyd
aspose/pyreflection.cp37-win_amd64.pyd
aspose/pyreflection.cp38-win_amd64.pyd
aspose/pyreflection.cp39-win_amd64.pyd
aspose/threed.cp310-win_amd64.pyd
aspose/threed.cp311-win_amd64.pyd
aspose/threed.cp35-win_amd64.pyd
aspose/threed.cp36-win_amd64.pyd
aspose/threed.cp37-win_amd64.pyd
aspose/threed.cp38-win_amd64.pyd
aspose/threed.cp39-win_amd64.pyd
aspose/__pyinstaller/__init__.pyi
aspose/__pyinstaller/hook-aspose.py
aspose/assemblies/pycore/WrpInterop.Aspose.PyCore.dll
aspose/assemblies/pygc/Aspose.PyGC.dll
aspose/assemblies/pyreflection/WrpInterop.Aspose.PyReflection.dll
aspose/assemblies/threed/Aspose.3D.dll
aspose/assemblies/threed/SkiaSharp.dll
aspose_3d-26.1.0.dist-info/METADATA
aspose_3d-26.1.0.dist-info/WHEEL
aspose_3d-26.1.0.dist-info/entry_points.txt
aspose_3d-26.1.0.dist-info/top_level.txt
aspose_3d-26.1.0.dist-info/RECORD