Metadata-Version: 2.1
Name: aspose-3d
Version: 26.1.0
Summary: Aspose.3D for Python via .NET is a cross-platform class library that enables your applications to connect with prevalent 3D document formats automatically without the 3D modeling and rendering software being installed on the server. Aspose.3D API lets engineers read, convert, build, alter and control the substance of the 3D document formats.
Home-page: https://products.aspose.com/3d/
Author: aspose-3d
License: https://company.aspose.com/legal/eula
Keywords: usdz,usd,vrml,3ds,ase,dae,fbx,u3d,x,dxf,rvm,jt,maya,blender,html5,gltf,glb,pdf,3mf,amf,obj,stl,xyz,obj,ply,pcd,3d,modeling,conversion,mesh,vr,ar,geometry,
Platform: win_amd64
Classifier: Intended Audience :: Developers
Classifier: Intended Audience :: Education
Classifier: Intended Audience :: Manufacturing
Classifier: Intended Audience :: Science/Research
Classifier: Operating System :: Microsoft :: Windows
Classifier: Operating System :: POSIX :: Linux
Classifier: Operating System :: MacOS :: MacOS X
Classifier: License :: Free To Use But Restricted
Classifier: License :: Other/Proprietary License
Classifier: Programming Language :: Python :: 3
Classifier: Programming Language :: Python :: 3 :: Only
Classifier: Programming Language :: Python :: 3.5
Classifier: Programming Language :: Python :: 3.6
Classifier: Programming Language :: Python :: 3.7
Classifier: Programming Language :: Python :: 3.8
Classifier: Programming Language :: Python :: 3.9
Classifier: Programming Language :: Python :: 3.10
Classifier: Programming Language :: Python :: 3.11
Classifier: Topic :: Software Development :: Libraries
Classifier: Topic :: Multimedia :: Graphics :: 3D Modeling
Classifier: Topic :: Multimedia :: Graphics :: 3D Rendering
Classifier: Topic :: Multimedia :: Graphics :: Graphics Conversion
Requires-Python: >=3.5,<3.12
